<annotation>
	<folder>my-project-name</folder>
	<filename>m19.jpg</filename>
	<path>/my-project-name/m19.jpg</path>
	<source>
		<database>Unspecified</database>
	</source>
	<size>
		<width>800</width>
		<height>560</height>
		<depth>3</depth>
	</size>
	<object>
		<name>Head</name>
		<pose>Unspecified</pose>
		<truncated>0</truncated>
		<difficult>0</difficult>
		<bndbox>
			<xmin>162</xmin>
			<ymin>70</ymin>
			<xmax>215</xmax>
			<ymax>158</ymax>
		</bndbox>
	</object>
	<object>
		<name>Head</name>
		<pose>Unspecified</pose>
		<truncated>0</truncated>
		<difficult>0</difficult>
		<bndbox>
			<xmin>306</xmin>
			<ymin>80</ymin>
			<xmax>346</xmax>
			<ymax>142</ymax>
		</bndbox>
	</object>
	<object>
		<name>Head</name>
		<pose>Unspecified</pose>
		<truncated>0</truncated>
		<difficult>0</difficult>
		<bndbox>
			<xmin>467</xmin>
			<ymin>90</ymin>
			<xmax>519</xmax>
			<ymax>162</ymax>
		</bndbox>
	</object>
	<object>
		<name>Head</name>
		<pose>Unspecified</pose>
		<truncated>0</truncated>
		<difficult>0</difficult>
		<bndbox>
			<xmin>598</xmin>
			<ymin>112</ymin>
			<xmax>642</xmax>
			<ymax>174</ymax>
		</bndbox>
	</object>
</annotation>